pretix_public_registrations/__init__.py
pretix_public_registrations/apps.py
pretix_public_registrations/forms.py
pretix_public_registrations/signals.py
pretix_public_registrations/urls.py
pretix_public_registrations/views.py
pretix_public_registrations/locale/django.pot
pretix_public_registrations/locale/de/LC_MESSAGES/django.mo
pretix_public_registrations/locale/de/LC_MESSAGES/django.po
pretix_public_registrations/static/pretix_public_registrations/.gitkeep
pretix_public_registrations/static/pretix_public_registrations/sorttable.js
pretix_public_registrations/static/pretix_public_registrations/ui.css
pretix_public_registrations/templates/pretix_public_registrations/.gitkeep
pretix_public_registrations/templates/pretix_public_registrations/front_page.html
pretix_public_registrations/templates/pretix_public_registrations/head.html
pretix_public_registrations/templates/pretix_public_registrations/settings.html
pretix_public_registrations-1.6.2.dist-info/licenses/LICENSE
pretix_public_registrations-1.6.2.dist-info/METADATA
pretix_public_registrations-1.6.2.dist-info/WHEEL
pretix_public_registrations-1.6.2.dist-info/entry_points.txt
pretix_public_registrations-1.6.2.dist-info/top_level.txt
pretix_public_registrations-1.6.2.dist-info/RECORD
