Metadata-Version: 2.4
Name: pretix-public-registrations
Version: 1.6.2
Summary: This plugin will give the option to attendees of an event to mark their
Author: Dominik Weitz
Author-email: Felix Schäfer <admin@kif.rocks>
Maintainer-email: Felix Schäfer <admin@kif.rocks>
License: MIT License
Project-URL: Homepage, https://gitlab.fachschaften.org/kif/pretix-public-registrations
Project-URL: Repository, https://gitlab.fachschaften.org/kif/pretix-public-registrations
Project-URL: Tracker, https://gitlab.fachschaften.org/kif/pretix-public-registrations/-/issues
Project-URL: pretix Marketplace, https://marketplace.pretix.eu/products/public-registrations/
Keywords: pretix,public registrations
Classifier: Development Status :: 5 - Production/Stable
Classifier: Environment :: Plugins
Classifier: Framework :: Django
Classifier: License :: OSI Approved :: MIT License
Classifier: Programming Language :: Python :: 3
License-File: LICENSE
Dynamic: license-file
